ukpostcodeutils/__init__.py
ukpostcodeutils/validation.py
ukpostcodeutils/test/__init__.py
ukpostcodeutils/test/test_validation.py
uk_postcode_utils-1.1.dist-info/LICENSE.txt
uk_postcode_utils-1.1.dist-info/METADATA
uk_postcode_utils-1.1.dist-info/WHEEL
uk_postcode_utils-1.1.dist-info/top_level.txt
uk_postcode_utils-1.1.dist-info/RECORD
