Metadata-Version: 1.1
Name: uk-postcode-utils
Version: 1.1
Summary: Functions for handling UK postcodes.
Home-page: https://pypi.python.org/pypi/uk-postcode-utils/
Author: Matthew Somerville
Author-email: matthew@mysociety.org
License: LICENSE.txt
Platform: UNKNOWN
Classifier: Development Status :: 5 - Production/Stable
Classifier: Environment :: Web Environment
Classifier: License :: OSI Approved :: GNU Affero General Public License v3
Classifier: Intended Audience :: Developers
Classifier: Programming Language :: Python
Classifier: Programming Language :: Python :: 2
Classifier: Programming Language :: Python :: 3
Classifier: Topic :: Scientific/Engineering :: GIS
